easyMD/ logging_config.py
easyMD/__init__.py
easyMD/cli.py
easyMD/io.py
easyMD/analysis/__init__.py
easyMD/analysis/trajectory.py
easyMD/app/__init__.py
easyMD/app/prepare_system.py
easyMD/app/process_trajectory.py
easyMD/app/run_simulation.py
easyMD/prep/__init__.py
easyMD/prep/data.py
easyMD/prep/forcefield.py
easyMD/prep/ligand.py
easyMD/prep/rcsb.py
easyMD/prep/structure.py
easyMD/prep/system.py
easyMD/simulation/__init__.py
easymd-3.2.3.dist-info/licenses/LICENSE
easymd-3.2.3.dist-info/METADATA
easymd-3.2.3.dist-info/WHEEL
easymd-3.2.3.dist-info/entry_points.txt
easymd-3.2.3.dist-info/top_level.txt
easymd-3.2.3.dist-info/RECORD
