Metadata-Version: 2.4
Name: easyMD
Version: 3.2.3
Summary: A set of utilities and notebooks for running OpenMM simulations.
Home-page: https://github.com/degrado-lab/easyMD
Author: Nicholas Freitas
Author-email: nicholas.freitas@ucsf.edu
License: MIT
Classifier: Programming Language :: Python :: 3
Classifier: License :: OSI Approved :: MIT License
Classifier: Operating System :: OS Independent
Requires-Python: >=3.10
License-File: LICENSE
Requires-Dist: typer>=0.16.0
Requires-Dist: tqdm
Requires-Dist: requests
Requires-Dist: termol
Dynamic: author
Dynamic: author-email
Dynamic: classifier
Dynamic: description
Dynamic: description-content-type
Dynamic: home-page
Dynamic: license
Dynamic: license-file
Dynamic: requires-dist
Dynamic: requires-python
Dynamic: summary
